{
  "version": 2,
  "major_version": 1,
  "groups": [
    {
      "id": "a20_plus_licenses",
      "name": "DDR A20+ Licenses",
      "songs": [
        { "skillId": "dq6b0b6OD9DbDPQOO608oDo8Q80ODIqO", "title": "Crazy Hot" },
        { "skillId": "DDPPI6IIi0i9looibDbiODoOPOl6ID8i", "title": "Feidie" },
        { "skillId": "QbdQold98oq9lODoIloIbPiIqld6i0Qb", "title": "GUILTY DIAMONDS" },
        { "skillId": "oI0P1oq89blIobOd0QqilPqd9Didd0OD", "title": "I believe what you said" },
        { "skillId": "I9P1dbOqD1qIP8bd9O80Ooo869bldobD", "title": "No Life Queen [DJ Command Remix]" },
        { "skillId": "00ibl6biOOOdDd96OP0P0i8iObo8i09d", "title": "Realize" },
        { "skillId": "id099qDODdQ9Ooi9dq1I981Diq101QDO", "title": "Seize The Day" },
        { "skillId": "QIDqidPlPQll9q6Il0dblIo609lii1di", "title": "SHINY DAYS" },
        { "skillId": "POdll6oPi1dd68q19q8ID6iQ6d08bl99", "title": "Together Going My Way" },
        { "skillId": "IObPQb9QlP0iIiboObPoPqIqDo0O11Qi", "title": "春を告げる" },
        { "skillId": "6lb86I9Q18Di6do1lDdod8b1Po688019", "title": "恋" },
        { "skillId": "PIP1OIoObQ11Q0Po6idiloqOl9OQqqdd", "title": "なだめスかし Negotiation" },
        { "skillId": "1qPbqd11l6b8ibq1ODQ6di90PIo0D618", "title": "ロキ(w/緒方恵美)" },
        { "skillId": "o1d0DDobPPPlq0l8Qli1d6ODI8ldo1qb", "title": "シル・ヴ・プレジデント" },
        { "skillId": "o8IDq8P8lP9o8IIO6lPPqqQP91bo0ddl", "title": "サイカ" },
        { "skillId": "oIid19qq6dQ00O16IDiQ991D9OqdQil0", "title": "思想犯" },
        { "skillId": "QiOl969Iq1Pl6o60QOQ9PooDbbiOPioo", "title": "スカイクラッドの観測者" },
        { "skillId": "dbod1o098DoibO0PoiPIiQ11Pdlqdoo9", "title": "テレキャスタービーボーイ" },
        { "skillId": "D6b8boIiOqQOq1QP9D1qd08I6Q0IIqq9", "title": "雑草魂なめんなよ！" }
      ]
    },
    {
      "id": "a3_extra_exclusive",
      "name": "DDR A3 Extra Exclusive",
      "songs": [
        { "skillId": "QD8l9QQd89PO9ql1iOD0dO69OQ1DldbP", "title": "Eon Break" },
        { "skillId": "IiiqDblQ8Oqlbo8OOiqI6IqO6P8I8I1d", "title": "Pure Rude" }
      ]
    },
    {
      "id": "bpl_ouen_stamp_rally",
      "name": "BPL応援 楽曲解禁スタンプラリー",
      "unlock": "single",
      "songs": [
        { "skillId": "dI1Ii100bQ6006l89diod0d116diOl8D", "title": "Uh-Oh" },
        { "skillId": "l0OPoQ1O8q8DPDo0Iol6qD6DiIqdD9P9", "title": "灼熱 Pt.2 Long Train Running" }
      ]
    },
    {
      "id": "bemani_2021_collab_event",
      "name": "BEMANI 2021真夏の歌合戦5番勝負",
      "unlock": "single",
      "songs": [
        { "skillId": "Odb0b0ld6P80b8b6QD0IIO866iq8OQ0b", "title": "鋳鉄の檻" },
        { "skillId": "19old9dq1q9DilPQDol88d19dI96blb6", "title": "MOVE! (We Keep It Movin')" },
        { "skillId": "ooiqoi6Q0dil6b10QOq8DiOIiq9iQb10", "title": "LIKE A VAMPIRE" },
        { "skillId": "boqo0IoO8DodOl99Q8P8qOi8PqDq11b1", "title": "スーパー戦湯ババンバーン" },
        { "skillId": "lilO9P0i1dlOl1PI6dQbiob1iP0dliOQ", "title": "Globe Glitter" },
        { "skillId": "IPid909iDid06d68IDo816OqbdQq8O0O", "title": "ユメブキ" }
      ]
    },
    {
      "id": "a3_course_trial",
      "name": "DDR A3 Course Trial",
      "unlock": "single",
      "songs": [
        { "skillId": "8o08l8DPiO01dlo1OI8DqQDq9lQ1bPq1", "title": "PERSIAN LAND" },
        { "skillId": "l6oP66ODld89Q99o0lDPP90qdbo11PPQ", "title": "ON-DO" },
        { "skillId": "qi0lbbDIo8Qlo9IiD8oqqo69DIPQ1IIO", "title": "Come Back to Me (Feel It)" },
        { "skillId": "dQdo08Qb6bOPIl8686DPDd60I1oqidIP", "title": "Debug Dance" },
        { "skillId": "lb969IOOoI06P18PPq81o1lPD1b1OqqI", "title": "Get it" },
        { "skillId": "oP8iIdilQ0QiDllqDbDIOl0iQPd9PQ9I", "title": "Crystarium" },
        { "skillId": "6oIO00P8bdqqbP9qlqIqDP1Q1d9PD0qi", "title": "insist" },
        { "skillId": "1088IDQiIDl6I888OQi60l66DP6D0qOl", "title": "Phlox" },
        { "skillId": "111O66bbPIQb09PlIoolIOD666QqqIdP", "title": "アドレナリン" },
        { "skillId": "qb9Od0IQI16b6D9PP0O6ilqoq0dDQO66", "title": "羊皮紙の上の銀河" },
        { "skillId": "8q96ObOdqPq8blPob9QdDq9b1iQoIQOI", "title": "メンタンピンドラドラ" },
        { "skillId": "Oqo009llDdDIODldDOI6OIolqlI9PI0d", "title": "とこにゃつ☆トロピカル" },
        { "skillId": "6dQQd1d1OQlqQdQ98i01DQ1i9P6QDQdQ", "title": "BUTTERFLY (20th Anniversary Mix)", "difficulty_class": "challenge" },
        { "skillId": "8Io6oi89Q8DblI8IPdPPI0q98Ql9o98Q", "title": "CARTOON HEROES (20th Anniversary Mix)", "difficulty_class": "challenge" },
        { "skillId": "lIlQ8DbPP6Iil1DOlQ6d8IPQblDQ8IiI", "title": "HAVE YOU NEVER BEEN MELLOW (20th Anniversary Mix)", "difficulty_class": "challenge" },
        { "skillId": "D9IO16idQq6iiI88loI1i986lIID0O9O", "title": "LONG TRAIN RUNNIN' (20th Anniversary Mix)", "difficulty_class": "challenge" },
        { "skillId": "IbI90PiioDlqPP19D1odPPbP1PP0009O", "title": "SKY HIGH (20th Anniversary Mix)", "difficulty_class": "challenge" },
        { "skillId": "db8Ddd060IQ9lPlOlqO0PoPi0Qdb88o6", "title": "EMOTiON TRiPPER" },
        { "skillId": "", "title": "Urban Life" }
      ]
    },
    {
      "id": "a20_plus_cs_songs",
      "name": "A20+ CS Songs",
      "unlock": "all",
      "songs": [
        { "skillId": "dPb99qdqOQ1ioQ9Dqb1I9Q1bI0l0POII", "title": "1998 (Sparky 2006)" },
        { "skillId": "dll9D90dq1O09oObO66Pl8l9I9l0PbPP", "title": "B4U (The Acolyte mix)" },
        { "skillId": "OiDP81OQD0I810I89qdqIiDDP6i9qO0q", "title": "I'm Flying Away" },
        { "skillId": "O86D9iqi81QllOqP19dQqqId1qdIolqI", "title": "We Can Win The Fight" }
      ]
    },
    {
      "id": "music_pack_2023_1",
      "name": "music pack vol.15 and vol.16",
      "songs": [
        { "skillId": "ddq1DldlQ990iidO6O99q61bI1966Q0I", "title": "ALGORITHM", "difficulty_class": "challenge" },
        { "skillId": "PO68qOQI1oo8iQidQ9iIi9o9PPOD9OP6", "title": "Blue Rain", "difficulty_class": "challenge" }
      ],
      "unlock": "all"
    },
    {
      "id": "music_pack_2023_2",
      "name": "music pack vol.18",
      "songs": [
        { "skillId": "Q910dl1olqQ9qdO6q1q1O9Pq9b80lP6P", "title": "Hold Tight" },
        { "skillId": "iI90119iIb9l609b9981l8QDblDOb0I6", "title": "JUST BELIEVE" },
        { "skillId": "8dDQIPOo681iID8IiibbD8IbIldI86P1", "title": "LOVE SHINE (Body Grooverz 2006 mix)" },
        { "skillId": "i1ibID6lOoiPQ1lli86P9lIIqOoDlldQ", "title": "the beat" }
      ],
      "unlock": "all"
    },
    {
      "id": "music_pack_2023_3",
      "name": "music pack vol.17 and vol.18",
      "songs": [
        { "skillId": "ObI1oo6QlO981880DDDOlo8bQobI0I9P", "title": "Follow Tomorrow", "difficulty_class": "challenge" },
        { "skillId": "ibiD8868D116OIqbQ1DQ1IOb8OD1qQ98", "title": "Take A Step Forward", "difficulty_class": "challenge" }
      ],
      "unlock": "all"
    },
    {
      "id": "music_pack_2023_4",
      "name": "SPECIAL music pack feat.REFLEC BEAT vol.1",
      "songs": [
        { "skillId": "Id1D9D68OOqqqdDiOoDd6Q6oo10P6oqI", "title": "Flip Flap" },
        { "skillId": "8IDiil0bDd00P1l1iQiq9DP6bO0b8dQb", "title": "GLITTER" },
        { "skillId": "9lo10Dl06QIblQqOOid1qi0bd10I9lQ9", "title": "Valanga" },
        { "skillId": "O6P1dIO0IDO6o8ib6i8oP86Qb9D08idd", "title": "カラフルミニッツ" }
      ],
      "unlock": "all"
    },
    {
      "id": "music_pack_2023_5",
      "name": "SPECIAL music pack feat.REFLEC BEAT vol.2",
      "songs": [
        { "skillId": "6qPlI8DQPoDIo6D819boPioIPPDIPblq", "title": "Broken" },
        { "skillId": "bOQ0dIIIilDD9Do6qIDdlObQdo01DD80", "title": "Playing With Fire" },
        { "skillId": "Odd6dI6o98O68I98l6q8PqODIooQO9ol", "title": "Towards The Horizon" },
        { "skillId": "iQDQD8889Q8O018Oi60I69D6qD6odDI0", "title": "伐折羅-vajra-" }
      ],
      "unlock": "all"
    },
    {
      "id": "music_pack_2023_6",
      "name": "music pack vol.19 and vol.20",
      "songs": [
        { "skillId": "oPP1Pdl6Qdlb8oq10PP1doDibdbbl9bl", "title": "朧 (dj TAKA Remix)", "difficulty_class": "challenge" },
        { "skillId": "Pld9iO6oi9qlDD08l8QDdIi6d6Q6iDd1", "title": "Programmed Universe", "difficulty_class": "challenge" }
      ],
      "unlock": "all"
    },
    {
      "id": "music_pack_2023_7",
      "name": "music pack vol.22",
      "songs": [
        { "skillId": "0OQiI9qD6OiodDoQlPllqPoPoqi98D8P", "title": "Open Your Eyes"  },
        { "skillId": "oloqOddo8oI1696Oqidb081ldlPQ89qO", "title": "Racing with Time (NAOKI's 999 remix)" },
        { "skillId": "8QPioDo6lIDdq861DDooq1O9dqdOOPiD", "title": "SAY A PRAYER" },
        { "skillId": "bo8DPdi09odO8oq9ql0iI8booOioOqi0", "title": "Surrender (PureFocus remix)" }
      ],
      "unlock": "all"
    },
    {
      "id": "music_pack_2023_8",
      "name": "music pack vol.21 and vol.22",
      "songs": [
        { "skillId": "l666Dd0bIO9O69boPd898b19bPDo1IdO", "title": "starmine", "difficulty_class": "challenge" },
        { "skillId": "I6dI99IOolDD6l6Q1ooPIiDO8Odq0QIP", "title": "UNBELIEVABLE (Sparky remix)", "difficulty_class": "challenge" }
      ],
      "unlock": "all"
    },
    {
      "id": "music_pack_2023_9",
      "name": "BPL S2 music pack vol 0-8",
      "songs": [
        { "skillId": "dlq91b19ld10IdIqQ9q99O8QDOOi18dq", "title": "BREAKING THE FUTURE" },
        { "skillId": "688O16o80Iib0DPI8oQOIOdbIdQq0P1Q", "title": "Aria" },
        { "skillId": "DdIQdo1D01PblPQd06696dPq610o1lIl", "title": "Rise As One" },
        { "skillId": "b0o6bl18Q1bqI9o9oqQ9POoP8DiDDibP", "title": "Drive Away" },
        { "skillId": "1IdqDqDdd08dboO911P6OQ8lobb16PDd", "title": "Chromatic Burst" },
        { "skillId": "8d9Q0olQ980lQdPIdqbIiD8o1l1dQPI0", "title": "GLOW THE CROWN" },
        { "skillId": "68iObo1dP91oqDQ18iiiPQDDb8O6ddq6", "title": "SMASH" },
        { "skillId": "919bPoOo9QO6dODOI6d0loO6qo6OqDlI", "title": "Complete Game Victory" },
        { "skillId": "OQO1Di8IQIQqP1d81d1ID9QD110b0888", "title": "Abrupt Madness" },
        { "skillId": "dlq91b19ld10IdIqQ9q99O8QDOOi18dq", "title": "BREAKING THE FUTURE", "difficulty_class": "challenge" }
      ],
      "unlock": "all"
    },
    {
      "id": "music_pack_2023_10",
      "name": "SPECIAL music pack feat.UNDERTALE",
      "songs": [
        { "skillId": "I6oq8ODq6DOOiqod1iI1109DO1II9iiO", "title": "Battle Against a True Hero" },
        { "skillId": "qqdlo1QOQo6QIi8PqOi8iIOO0il1IblQ", "title": "Death by Glamour" },
        { "skillId": "Qid6OQOIibbOiDo808oq9oQO668bDodP", "title": "Finale" }
      ],
      "unlock": "all"
    },
    {
      "id": "music_pack_2023_11",
      "name": "SPECIAL music pack feat.Touhou Project vol.3",
      "songs": [
        { "skillId": "8Oq81q8q1Q9D0l0PO0bQQ00l9P19didi", "title": "HANIPAGANDA" },
        { "skillId": "Q86bq1iQDIqDllbdD6ldIO089q8Q1689", "title": "LOVE EAST" },
        { "skillId": "8069d8dPiqloqD8i8od1o1Pq1Q6Q8i9D", "title": "トランスダンスアナーキー" }
      ],
      "unlock": "all"
    },
    {
      "id": "music_pack_2023_12",
      "name": "SPECIAL music pack feat.Touhou Project vol.4",
      "songs": [
        { "skillId": "lob09DPQD0Dl6Q09dbq8biIb6QqDql8i", "title": "INFINITE WORLD" },
        { "skillId": "99ll6bPDDPqQ8boPIQbdQ6bPo8bl69O9", "title": "Kill The Night" },
        { "skillId": "dQQ6dQb1dQDd8bPqIPI0blb11ioq1QQo", "title": "しゅわスパ大作戦☆" }
      ],
      "unlock": "all"
    },
    {
      "id": "music_pack_2023_13",
      "name": "SPECIAL music pack feat.Touhou Project vol.3 & 4",
      "songs": [
        { "skillId": "I90bd6obO890P0d1iiPD0dol8o8QloQD", "title": "Grip & Break down !!", "difficulty_class": "challenge" },
        { "skillId": "I0091lboOD1Dii10dQ0qbDqil69PQ0io", "title": "WARNING×WARNING×WARNING", "difficulty_class": "challenge" }
      ],
      "unlock": "all"
    },
    {
      "id": "a3_dancearound_collab",
      "name": "DANCE aROUND × DDR 2022夏のMUSIC CHOICE",
      "unlock": "single",
      "songs": [
        { "skillId": "iiIblq9IDiOill8qdI68OOIPq6OPdiDo", "title": "Easy Peasy" },
        { "skillId": "iIDOlq6QoQPiqoii0iiDOiI9ODiQOIDb", "title": "Go Down" },
        { "skillId": "88Qq96qbdd69bqI089600l9bDDdiQI0l", "title": "Prettiful!" },
        { "skillId": "oilPP86l0PPq6Db0qqibQlqDiIOD0l1O", "title": "You You You" }
      ]
    },
    {
      "id": "extra_savior_a3",
      "name": "EXTRA SAVIOR A3",
      "unlock": "single",
      "songs": [
        { "skillId": "0iII09bDqIbOQDDoo8lO8DOOQdiP1Iob", "title": "Good Sound United" },
        { "skillId": "boDqoIDqDlP1io6bQ0O10diDbbqOD96I", "title": "Unreality" }
      ]
    },
    {
      "id": "extra_savior_a3_summer_vacation",
      "name": "Enjoy Summer Vacation!",
      "unlock": "single",
      "songs": [
        { "skillId": "IidO8qlodqdoioodqqb9Dqiq991Ilo10", "title": "リリーゼと炎龍レーヴァテイン" },
        { "skillId": "ibOId89QQPI6dli9I6PO09Qo86686O6i", "title": "MANA" }
      ]
    },
    {
      "id": "extra_savior_a3_collab_event",
      "name": "BEMANI 2021真夏の歌合戦5番勝負",
      "unlock": "single",
      "songs": [
        { "skillId": "qIIDP8iPlII9qlOQIIol0i81b0d68qo8", "title": "MA・TSU・RI" },
        { "skillId": "OoQiq8OiPbIPI80OqOlliP661bOIDd9o", "title": "チュッチュ♪マチュピチュ" },
        { "skillId": "I86OI9lQ1qQ66dPDlddo8PoPo01PO66i", "title": "斑咲花" },
        { "skillId": "9b60DI1OQddDI6D9D1qPoDPODD19Db8d", "title": "DUAL STRIKER" },
        { "skillId": "bqoboI0o8lIObPPdqq8lDDdI8b1QPDb1", "title": "恋愛観測 -2021真夏のエンディング ver.-" }
      ]
    },
    {
      "id": "2022_halloween",
      "name": "Boo! Trick or treat!",
      "songs": [
        { "skillId": "IPdQ8qIqPiIdqQloI1dQQ688O0qlOQQo", "title": "BONE BORN" },
        { "skillId": "Pb0D8b8b8PoDIO9Q9DbiQiI8qi0D89D8", "title": "惑星☆ロリポップ" }
      ]
    },
    {
      "id": "2022_christmas",
      "name": "Crystal clear winter",
      "songs": [
        { "skillId": "8ql0DIiI0D9D1OP0qb8olo9bIQdP0ddq", "title": "Snow Garland Fairy" }
      ]
    },
    {
      "id": "2023_valentines",
      "name": "恋せよDDRのバレンタイン＆ホワイトデー2023",
      "songs": [
        { "skillId": "0q90DbbI1O90D91I8ddDdDlP9IdoQ0oo", "title": "みゅ、みゅ、M&uuml;llる" }
      ]
    },
    {
      "id": "2023_jubeat_collab",
      "name": "春を呼ぶ桜の祝祭",
      "songs": [
        { "skillId": "Od6bOOb69PqbqPdb6lO1QI66DOqo0POO", "title": "chaplet" },
        { "skillId": "DID6l8bbD0D6661lPiP6QIQ1dPbb010d", "title": "spring pony" }
      ]
    },
    {
      "id": "kac_2023",
      "name": "KONAMI Arcade Championship (2023) Entry Songs",
      "songs": [
        { "skillId": "ob6IPbiqD969Q66808obd908DI81bqPi", "title": "I-W-U (I Want U)" },
        { "skillId": "o89biodIl0Oo1bQqll86QDi0oQQd61Db", "title": "Sparkle Dreams" },
        { "skillId": "08O1i8ib1lDPbdOoPlD069PoOI1860qi", "title": "mathematical good-bye" },
        { "skillId": "1II6199qOd1bo0P0D19Q9qd06ll1QOl9", "title": "ROCK THE PARTY" }
      ]
    },
    {
      "id": "baby_lon_galaxy",
      "name": "BABY LON'S GALAXY",
      "songs": [
        { "skillId": "qQd06O6d19ODl0QP8l6Q8lPlloo69ddP", "title": "BLUE FOG, SILVER BULLET." },
        { "skillId": "Q99q619i0lDqll6Q0lq8l1oQ0qPO8o6I", "title": "Electronic Sports Complex" },
        { "skillId": "D1QDql1OQDl1dblId0P81Q999dO9POoP", "title": "ｍｅｍｏｒｙ／／ＤＡＴＡＭＯＳＨＥＲ" },
        { "skillId": "bll06Di6q1QOlddDlPDPiQDDI09bOOoP", "title": "Come To m1dy" },
        { "skillId": "lliDD9qPqiIDI8P9bb18IO60l9D061Io", "title": "SISYPHUS" },
        { "skillId": "q96q9D9oIIOQl8QQ60ii19P0Dbq8Q609", "title": "New Millennium" },
        { "skillId": "", "title": "鳳" }
      ]
    },
    {
      "id": "a20_legend_license",
      "name": "\"Legend License\" Remixes",
      "songs": [
        { "skillId": "6dQQd1d1OQlqQdQ98i01DQ1i9P6QDQdQ", "title": "BUTTERFLY (20th Anniversary Mix)" },
        { "skillId": "8Io6oi89Q8DblI8IPdPPI0q98Ql9o98Q", "title": "CARTOON HEROES (20th Anniversary Mix)" },
        { "skillId": "lIlQ8DbPP6Iil1DOlQ6d8IPQblDQ8IiI", "title": "HAVE YOU NEVER BEEN MELLOW (20th Anniversary Mix)" },
        { "skillId": "D9IO16idQq6iiI88loI1i986lIID0O9O", "title": "LONG TRAIN RUNNIN' (20th Anniversary Mix)" },
        { "skillId": "IbI90PiioDlqPP19D1odPPbP1PP0009O", "title": "SKY HIGH (20th Anniversary Mix)" }
      ]
    },
    {
      "id": "a3_golden_league_bronze",
      "name": "GOLDEN LEAGUE BRONZE Class",
      "unlock": "all",
      "songs": [
        { "skillId": "b1QllqO8oQdqo086QdIlIblDDbPodDoP", "title": "Lose Your Sense" },
        { "skillId": "O6q9qPQ1q69ddPl6DPO0bQO6989QO1ii", "title": "Sector" },
        { "skillId": "iQ9qQ8Iob108iPD9D0bdoIol0d81IOdo", "title": "Ability" },
        { "skillId": "iq6b9lP6qQQIOIPQDdPD8ld1o9891Pq9", "title": "SURVIVAL AT THE END OF THE UNIVERSE" }
      ]
    },
    {
      "id": "a3_golden_league_silver",
      "name": "GOLDEN LEAGUE SILVER Class",
      "unlock": "all",
      "songs": [
        { "skillId": "iQi8Oool866oDQ6i660o88b86689QiOb", "title": "Jungle Dance" },
        { "skillId": "PIl8P90Pll19Pido608olD61QIqq0b9d", "title": "Rave in the Shell" },
        { "skillId": "i6bIQ6D0P09olqbOiP8I919006DdII1P", "title": "Not Alone" },
        { "skillId": "lOOo9bPb09dIOb6Po19bqqbqOlb8Dq0i", "title": "GROOVE 04" }
      ]
    },
    {
      "id": "a3_golden_league_gold",
      "name": "GOLDEN LEAGUE GOLD Class",
      "unlock": "all",
      "songs": [
        { "skillId": "", "title": "Euphoric Fragmentation" },
        { "skillId": "", "title": "Continue to the real world?" }
      ]
    }
  ],
  "default_ignore_list": "A20PLUS_US",
  "lists": [
    {
      "id": "A3_US",
      "name": "DDR A3 (White) (US)",
      "base_version": "DDR_A3",
      "locked_groups": [
        "a20_plus_licenses",
        "a3_extra_exclusive",
        "a3_golden_league_bronze",
        "a3_golden_league_silver",
        "a3_golden_league_gold"
      ],
      "groups": [
        "bpl_ouen_stamp_rally",
        "bemani_2021_collab_event",
        "a3_course_trial",
        "extra_savior_a3",
        "extra_savior_a3_summer_vacation",
        "extra_savior_a3_collab_event",
        "a20_plus_cs_songs",
        "music_pack_2023_1",
        "music_pack_2023_2",
        "music_pack_2023_3",
        "music_pack_2023_4",
        "music_pack_2023_5",
        "music_pack_2023_6",
        "music_pack_2023_7",
        "music_pack_2023_8",
        "music_pack_2023_9",
        "music_pack_2023_10",
        "music_pack_2023_11",
        "music_pack_2023_12",
        "music_pack_2023_13"
      ],
      "songs": [
        { "skillId": "IlbI1QQOPI0o0IdoPI6QPldqQob16DOq", "title": "ナイト・オブ・ナイツ (Ryu☆Remix)" },
        { "skillId": "illQ66d0QlbDl18OOb8P0ODD0oDP19PQ", "title": "令和" },
        { "skillId": "i0P1O6lbP1oDd6q6b08iPPoq6iPdI818", "title": "最終鬼畜妹フランドール・Ｓ" }
      ]
    },
    {
      "id": "A3_JP",
      "name": "DDR A3 (White) (JP)",
      "base_version": "DDR_A3",
      "locked_groups": [
        "a3_extra_exclusive",
        "a3_golden_league_bronze",
        "a3_golden_league_silver",
        "a3_golden_league_gold"
      ],
      "groups": [
        "bpl_ouen_stamp_rally",
        "bemani_2021_collab_event",
        "a3_course_trial",
        "extra_savior_a3",
        "extra_savior_a3_summer_vacation",
        "extra_savior_a3_collab_event",
        "a20_plus_cs_songs",
        "music_pack_2023_1",
        "music_pack_2023_2",
        "music_pack_2023_3",
        "music_pack_2023_4",
        "music_pack_2023_5",
        "music_pack_2023_6",
        "music_pack_2023_7",
        "music_pack_2023_8",
        "music_pack_2023_9",
        "music_pack_2023_10",
        "music_pack_2023_11",
        "music_pack_2023_12",
        "music_pack_2023_13"
      ]
    },
    {
      "id": "A3_GOLD_CAB",
      "name": "DDR A3 20th Anniversary (Gold) (JP)",
      "base_version": "DDR_A3",
      "locked_groups": [
        "a3_extra_exclusive"
      ],
      "groups": [
        "bpl_ouen_stamp_rally",
        "bemani_2021_collab_event",
        "a3_course_trial",
        "extra_savior_a3",
        "extra_savior_a3_summer_vacation",
        "extra_savior_a3_collab_event",
        "a20_plus_cs_songs",
        "music_pack_2023_1",
        "music_pack_2023_2",
        "music_pack_2023_3",
        "music_pack_2023_4",
        "music_pack_2023_5",
        "music_pack_2023_6",
        "music_pack_2023_7",
        "music_pack_2023_8",
        "music_pack_2023_9",
        "music_pack_2023_10",
        "music_pack_2023_11",
        "music_pack_2023_12",
        "music_pack_2023_13",
        "a3_golden_league_bronze",
        "a3_golden_league_silver",
        "a3_golden_league_gold"
      ]
    },
    {
      "id": "A20PLUS_US",
      "name": "DDR A20+",
      "base_version": "DDR_A20_PLUS"
    },
    {
      "id": "ALL_MUSIC_A20PLUS",
      "name": "All Songs",
      "base_version": "DDR_A20_PLUS"
    },
    {
      "id": "ALL_MUSIC",
      "name": "All Songs",
      "base_version": "DDR_A3"
    }
  ]
}
